dumper/__init__.py
dumper/config.py
dumper/db_inspector.py
dumper/dump.py
dumper/main.py
dumper/models.py
dumper/utils.py
database_dumper-0.1.0.dist-info/METADATA
database_dumper-0.1.0.dist-info/WHEEL
database_dumper-0.1.0.dist-info/entry_points.txt
database_dumper-0.1.0.dist-info/RECORD
