Metadata-Version: 2.4
Name: database-dumper
Version: 0.1.0
Summary: Add your description here
Author-email: PavukEdya <slaefir@mail.ru>
License: MIT
Requires-Python: >=3.12
Requires-Dist: geoalchemy2>=0.17.1
Requires-Dist: psycopg2>=2.9.10
Requires-Dist: python-dotenv>=1.1.0
Requires-Dist: ruff>=0.11.7
Requires-Dist: sqlalchemy>=2.0.40
